{
  "db_name": "PostgreSQL",
  "query": "SELECT * FROM \"transaction\" ORDER BY created_at desc",
  "describe": {
    "columns": [
      {
        "ordinal": 0,
        "name": "id",
        "type_info": "Uuid"
      },
      {
        "ordinal": 1,
        "name": "user_id",
        "type_info": "Uuid"
      },
      {
        "ordinal": 2,
        "name": "casino_id",
        "type_info": "Uuid"
      },
      {
        "ordinal": 3,
        "name": "cost",
        "type_info": "Int4"
      },
      {
        "ordinal": 4,
        "name": "benefit",
        "type_info": "Int4"
      },
      {
        "ordinal": 5,
        "name": "created_at",
        "type_info": "Timestamp"
      },
      {
        "ordinal": 6,
        "name": "updated_at",
        "type_info": "Timestamp"
      },
      {
        "ordinal": 7,
        "name": "notes",
        "type_info": "Text"
      }
    ],
    "parameters": {
      "Left": []
    },
    "nullable": [
      false,
      false,
      false,
      false,
      false,
      false,
      false,
      true
    ]
  },
  "hash": "b5d5ab5c73c31b2806e53682c1fd5d4ded5fb0a650fd5760a4d754ca445af96b"
}
